{"City": "Alden", "Address Description": "", "County": "Hardin", "Address": "1012  Water St ", "geo": [{"geometry": {"bounds": {"northeast": {"lat": 42.5193775, "lng": -93.3745843}, "southwest": {"lat": 42.5193668, "lng": -93.3745957}}, "location": {"lat": 42.5193775, "lng": -93.3745843}, "viewport": {"northeast": {"lat": 42.5207211302915, "lng": -93.3732410197085}, "southwest": {"lat": 42.5180231697085, "lng": -93.37593898029151}}, "location_type": "RANGE_INTERPOLATED"}, "address_components": [{"long_name": "1012", "types": ["street_number"], "short_name": "1012"}, {"long_name": "Water Street", "types": ["route"], "short_name": "Water St"}, {"long_name": "Alden", "types": ["locality", "political"], "short_name": "Alden"}, {"long_name": "Alden", "types": ["administrative_area_level_3", "political"], "short_name": "Alden"}, {"long_name": "Hardin", "types": ["administrative_area_level_2", "political"], "short_name": "Hardin"}, {"long_name": "Iowa", "types": ["administrative_area_level_1", "political"], "short_name": "IA"}, {"long_name": "United States", "types": ["country", "political"], "short_name": "US"}, {"long_name": "50006", "types": ["postal_code"], "short_name": "50006"}], "partial_match": true, "formatted_address": "1012 Water Street, Alden, IA 50006, USA", "types": ["street_address"]}], "Property Name": "Alden Public Library", "Listed Date": "17-Mar-81"}