{"County": "Crawford", "Property Name": "Beaver Creek Bridge", "Address": "  180th St ", "Address Description": "4.5 miles NW of Schleswing, between B&C Ave, over Beaver Cr", "City": "Schleswig", "Listed Date": "25-Jun-98", "geo": [{"geometry": {"location_type": "APPROXIMATE", "bounds": {"northeast": {"lat": 42.17107600000001, "lng": -95.42591499999999}, "southwest": {"lat": 42.14690100000001, "lng": -95.44433099999999}}, "viewport": {"northeast": {"lat": 42.17107600000001, "lng": -95.42591499999999}, "southwest": {"lat": 42.14690100000001, "lng": -95.44433099999999}}, "location": {"lat": 42.1652658, "lng": -95.4369432}}, "address_components": [{"long_name": "Schleswig", "types": ["locality", "political"], "short_name": "Schleswig"}, {"long_name": "Otter Creek", "types": ["administrative_area_level_3", "political"], "short_name": "Otter Creek"}, {"long_name": "Crawford", "types": ["administrative_area_level_2", "political"], "short_name": "Crawford"}, {"long_name": "Iowa", "types": ["administrative_area_level_1", "political"], "short_name": "IA"}, {"long_name": "United States", "types": ["country", "political"], "short_name": "US"}, {"long_name": "51461", "types": ["postal_code"], "short_name": "51461"}], "partial_match": true, "formatted_address": "Schleswig, IA 51461, USA", "types": ["locality", "political"]}]}