{"City": "Brooklyn", "Address Description": "", "County": "Poweshiek", "Address": "154  Front St ", "geo": [{"geometry": {"bounds": {"northeast": {"lat": 41.728337, "lng": -92.4464842}, "southwest": {"lat": 41.72832349999999, "lng": -92.44648810000001}}, "location": {"lat": 41.728337, "lng": -92.44648810000001}, "viewport": {"northeast": {"lat": 41.7296792302915, "lng": -92.4451371697085}, "southwest": {"lat": 41.7269812697085, "lng": -92.44783513029151}}, "location_type": "RANGE_INTERPOLATED"}, "address_components": [{"long_name": "154", "types": ["street_number"], "short_name": "154"}, {"long_name": "West Front Street", "types": ["route"], "short_name": "W Front St"}, {"long_name": "Brooklyn", "types": ["locality", "political"], "short_name": "Brooklyn"}, {"long_name": "Bear Creek", "types": ["administrative_area_level_3", "political"], "short_name": "Bear Creek"}, {"long_name": "Poweshiek", "types": ["administrative_area_level_2", "political"], "short_name": "Poweshiek"}, {"long_name": "Iowa", "types": ["administrative_area_level_1", "political"], "short_name": "IA"}, {"long_name": "United States", "types": ["country", "political"], "short_name": "US"}, {"long_name": "52211", "types": ["postal_code"], "short_name": "52211"}], "partial_match": true, "formatted_address": "154 West Front Street, Brooklyn, IA 52211, USA", "types": ["street_address"]}], "Property Name": "Brooklyn Hotel", "Listed Date": "01-Oct-79"}