{"City": "Cedar Falls", "Address Description": "Franklin Ave and 1st St.", "County": "Black Hawk", "Address": "  Franklin Ave ", "geo": [{"geometry": {"bounds": {"northeast": {"lat": 42.5378362, "lng": -92.449083}, "southwest": {"lat": 42.5141307, "lng": -92.44999399999999}}, "location": {"lat": 42.5257408, "lng": -92.44950299999999}, "viewport": {"northeast": {"lat": 42.5378362, "lng": -92.44818951970849}, "southwest": {"lat": 42.5141307, "lng": -92.4508874802915}}, "location_type": "GEOMETRIC_CENTER"}, "address_components": [{"long_name": "Franklin Street", "types": ["route"], "short_name": "Franklin St"}, {"long_name": "Cedar Falls", "types": ["locality", "political"], "short_name": "Cedar Falls"}, {"long_name": "Black Hawk", "types": ["administrative_area_level_2", "political"], "short_name": "Black Hawk"}, {"long_name": "Iowa", "types": ["administrative_area_level_1", "political"], "short_name": "IA"}, {"long_name": "United States", "types": ["country", "political"], "short_name": "US"}, {"long_name": "50613", "types": ["postal_code"], "short_name": "50613"}], "partial_match": true, "formatted_address": "Franklin Street, Cedar Falls, IA 50613, USA", "types": ["route"]}], "Property Name": "Cedar Falls Ice House", "Listed Date": "21-Oct-77"}