{"City": "Des Moines", "Address Description": "307-311 Court Ave", "County": "Polk", "Address": "307  Court Ave ", "geo": [{"geometry": {"bounds": {"northeast": {"lat": 41.58526, "lng": -93.62077049999999}, "southwest": {"lat": 41.5852469, "lng": -93.6207759}}, "location": {"lat": 41.58526, "lng": -93.6207759}, "viewport": {"northeast": {"lat": 41.5866024302915, "lng": -93.61942421970849}, "southwest": {"lat": 41.5839044697085, "lng": -93.62212218029151}}, "location_type": "RANGE_INTERPOLATED"}, "address_components": [{"long_name": "307", "types": ["street_number"], "short_name": "307"}, {"long_name": "Court Avenue", "types": ["route"], "short_name": "Court Ave"}, {"long_name": "Des Moines", "types": ["locality", "political"], "short_name": "Des Moines"}, {"long_name": "Des Moines", "types": ["administrative_area_level_3", "political"], "short_name": "Des Moines"}, {"long_name": "Polk", "types": ["administrative_area_level_2", "political"], "short_name": "Polk"}, {"long_name": "Iowa", "types": ["administrative_area_level_1", "political"], "short_name": "IA"}, {"long_name": "United States", "types": ["country", "political"], "short_name": "US"}, {"long_name": "50309", "types": ["postal_code"], "short_name": "50309"}], "partial_match": true, "formatted_address": "307 Court Avenue, Des Moines, IA 50309, USA", "types": ["street_address"]}], "Property Name": "Des Moines Saddlery Company Building", "Listed Date": "27-Jun-85"}