{"City": "Davenport", "Address Description": "", "County": "Scott", "Address": "1003  Arlington Ct ", "geo": [{"geometry": {"bounds": {"northeast": {"lat": 41.53722459999999, "lng": -90.5611741}, "southwest": {"lat": 41.5372108, "lng": -90.56117449999999}}, "location": {"lat": 41.5372108, "lng": -90.56117449999999}, "viewport": {"northeast": {"lat": 41.5385666802915, "lng": -90.5598253197085}, "southwest": {"lat": 41.5358687197085, "lng": -90.5625232802915}}, "location_type": "RANGE_INTERPOLATED"}, "address_components": [{"long_name": "1003", "types": ["street_number"], "short_name": "1003"}, {"long_name": "Arlington Court", "types": ["route"], "short_name": "Arlington Ct"}, {"long_name": "Davenport", "types": ["locality", "political"], "short_name": "Davenport"}, {"long_name": "Scott", "types": ["administrative_area_level_2", "political"], "short_name": "Scott"}, {"long_name": "Iowa", "types": ["administrative_area_level_1", "political"], "short_name": "IA"}, {"long_name": "United States", "types": ["country", "political"], "short_name": "US"}, {"long_name": "52803", "types": ["postal_code"], "short_name": "52803"}], "partial_match": true, "formatted_address": "1003 Arlington Court, Davenport, IA 52803, USA", "types": ["street_address"]}], "Property Name": "Fisher, Lewis M., House", "Listed Date": "07-Jul-83"}