{"City": "Marion", "Address Description": "", "County": "Linn", "Address": "970  10th St ", "geo": [{"geometry": {"location": {"lat": 42.036043, "lng": -91.59980999999999}, "viewport": {"northeast": {"lat": 42.0443298, "lng": -91.5838026}, "southwest": {"lat": 42.0277552, "lng": -91.6158174}}, "location_type": "APPROXIMATE"}, "address_components": [{"long_name": "Granger House Museum", "types": ["point_of_interest", "establishment"], "short_name": "Granger House Museum"}, {"long_name": "970", "types": ["street_number"], "short_name": "970"}, {"long_name": "10th Street", "types": ["route"], "short_name": "10th St"}, {"long_name": "Marion", "types": ["locality", "political"], "short_name": "Marion"}, {"long_name": "Marion", "types": ["administrative_area_level_3", "political"], "short_name": "Marion"}, {"long_name": "Linn", "types": ["administrative_area_level_2", "political"], "short_name": "Linn"}, {"long_name": "Iowa", "types": ["administrative_area_level_1", "political"], "short_name": "IA"}, {"long_name": "United States", "types": ["country", "political"], "short_name": "US"}, {"long_name": "52302", "types": ["postal_code"], "short_name": "52302"}, {"long_name": "3572", "types": [], "short_name": "3572"}], "partial_match": true, "formatted_address": "Granger House Museum, 970 10th Street, Marion, IA 52302, USA", "types": ["point_of_interest", "museum", "establishment"]}], "Property Name": "Granger House", "Listed Date": "13-Aug-76"}