{"City": "Herrold", "Address Description": ".6 mi N of Herrold, crossing Beaver Creek", "County": "Polk", "Address": " NW 88th Ave ", "geo": [{"geometry": {"location": {"lat": 41.7205435, "lng": -93.7368894}, "viewport": {"northeast": {"lat": 41.7288713, "lng": -93.72088199999999}, "southwest": {"lat": 41.7122146, "lng": -93.7528968}}, "location_type": "APPROXIMATE"}, "address_components": [{"long_name": "Herrold", "types": ["locality", "political"], "short_name": "Herrold"}, {"long_name": "Jefferson", "types": ["administrative_area_level_3", "political"], "short_name": "Jefferson"}, {"long_name": "Polk", "types": ["administrative_area_level_2", "political"], "short_name": "Polk"}, {"long_name": "Iowa", "types": ["administrative_area_level_1", "political"], "short_name": "IA"}, {"long_name": "United States", "types": ["country", "political"], "short_name": "US"}, {"long_name": "50109", "types": ["postal_code"], "short_name": "50109"}], "partial_match": true, "formatted_address": "Herrold, IA 50109, USA", "types": ["locality", "political"]}], "Property Name": "Herrold Bridge", "Listed Date": "18-May-98"}