{"City": "Emmetsburg", "Address Description": "", "County": "Palo Alto", "Address": "2403 W 7th St ", "geo": [{"geometry": {"bounds": {"northeast": {"lat": 43.1138183, "lng": -94.6815103}, "southwest": {"lat": 43.1138049, "lng": -94.6815104}}, "location": {"lat": 43.1138183, "lng": -94.6815104}, "viewport": {"northeast": {"lat": 43.11516058029149, "lng": -94.68016136970849}, "southwest": {"lat": 43.1124626197085, "lng": -94.6828593302915}}, "location_type": "RANGE_INTERPOLATED"}, "address_components": [{"long_name": "2403", "types": ["street_number"], "short_name": "2403"}, {"long_name": "7th Street", "types": ["route"], "short_name": "7th St"}, {"long_name": "Emmetsburg", "types": ["locality", "political"], "short_name": "Emmetsburg"}, {"long_name": "Emmetsburg", "types": ["administrative_area_level_3", "political"], "short_name": "Emmetsburg"}, {"long_name": "Palo Alto", "types": ["administrative_area_level_2", "political"], "short_name": "Palo Alto"}, {"long_name": "Iowa", "types": ["administrative_area_level_1", "political"], "short_name": "IA"}, {"long_name": "United States", "types": ["country", "political"], "short_name": "US"}, {"long_name": "50536", "types": ["postal_code"], "short_name": "50536"}], "partial_match": true, "formatted_address": "2403 7th Street, Emmetsburg, IA 50536, USA", "types": ["street_address"]}], "Property Name": "Ormsby-Kelly House", "Listed Date": "29-Jul-77"}