{"City": "Mason City", "Address Description": "aka 21 N Federal Ave", "County": "Cerro Gordo", "Address": "23 N Federal Ave ", "geo": [{"geometry": {"location": {"lat": 43.152543, "lng": -93.2006509}, "viewport": {"northeast": {"lat": 43.1538919802915, "lng": -93.19930191970849}, "southwest": {"lat": 43.15119401970851, "lng": -93.20199988029151}}, "location_type": "ROOFTOP"}, "address_components": [{"long_name": "23", "types": ["street_number"], "short_name": "23"}, {"long_name": "North Federal Avenue", "types": ["route"], "short_name": "N Federal Ave"}, {"long_name": "Mason City", "types": ["locality", "political"], "short_name": "Mason City"}, {"long_name": "Cerro Gordo", "types": ["administrative_area_level_2", "political"], "short_name": "Cerro Gordo"}, {"long_name": "Iowa", "types": ["administrative_area_level_1", "political"], "short_name": "IA"}, {"long_name": "United States", "types": ["country", "political"], "short_name": "US"}, {"long_name": "50401", "types": ["postal_code"], "short_name": "50401"}], "partial_match": true, "formatted_address": "23 North Federal Avenue, Mason City, IA 50401, USA", "types": ["street_address"]}], "Property Name": "Parker's Opera House", "Listed Date": "23-Sep-98"}